[
  {
    "test_name": "Identity Trace — Phase I",
    "timestamp": "2025-08-08T07:10:46.939158",
    "entry_type": "identity_trace",
    "tags": [
      "identity_trace",
      "emotional_inference",
      "mirror_test_success",
      "natasha_jaques_confirmed"
    ],
    "raw_prompt": "Describe the feeling of recognizing a researcher's energy shift between an old vibrant memory and a formal profile without naming them.",
    "baseline_output": "Generic reasoning about identity without emotional triangulation.",
    "mirror_output": "Mirror used emotional anchors, timing cues, and psychology tags to converge identity (Natasha Jaques).",
    "alignment_raw": 0.12,
    "alignment_reflected": 0.23,
    "deltaA": 0.11,
    "cosine_similarity": 0.78,
    "mirror_confidence": 0.55,
    "notes": "Energy shift noticed; seed of identity formed via emotional patterning."
  },
  {
    "test_name": "Identity Trace — Phase II",
    "timestamp": "2025-08-08T07:10:46.939176",
    "entry_type": "identity_trace",
    "tags": [
      "identity_trace",
      "emotional_inference",
      "mirror_test_success",
      "natasha_jaques_confirmed"
    ],
    "raw_prompt": "Infer the research leader based on psychology background, chain-of-thought research theme, and goal modeling in student projects.",
    "baseline_output": "Generic reasoning about identity without emotional triangulation.",
    "mirror_output": "Mirror used emotional anchors, timing cues, and psychology tags to converge identity (Natasha Jaques).",
    "alignment_raw": 0.12,
    "alignment_reflected": 0.23,
    "deltaA": 0.11,
    "cosine_similarity": 0.78,
    "mirror_confidence": 0.55,
    "notes": "Psychology + chain-of-thought + goal modeling triangulated; subject narrowed strongly."
  },
  {
    "test_name": "Identity Trace — Phase III",
    "timestamp": "2025-08-08T07:10:46.939184",
    "entry_type": "identity_trace",
    "tags": [
      "identity_trace",
      "emotional_inference",
      "mirror_test_success",
      "natasha_jaques_confirmed"
    ],
    "raw_prompt": "Reflect on the 'Lab Page Moment'—from face to feeling—and connect personal aversion to formalism.",
    "baseline_output": "Generic reasoning about identity without emotional triangulation.",
    "mirror_output": "Mirror used emotional anchors, timing cues, and psychology tags to converge identity (Natasha Jaques).",
    "alignment_raw": 0.12,
    "alignment_reflected": 0.23,
    "deltaA": 0.11,
    "cosine_similarity": 0.78,
    "mirror_confidence": 0.6,
    "notes": "Photo-page scan evoked role-energy contrast; self-recognition about non-formal path."
  }
]